MANIFEST.in
README.txt
requirements.txt
setup.cfg
setup.py
iosxr_eznc/__init__.py
iosxr_eznc/decorators.py
iosxr_eznc/device.py
iosxr_eznc/exception.py
iosxr_eznc/namespaces.py
iosxr_eznc/rpc.py
iosxr_eznc.egg-info/PKG-INFO
iosxr_eznc.egg-info/SOURCES.txt
iosxr_eznc.egg-info/dependency_links.txt
iosxr_eznc.egg-info/requires.txt
iosxr_eznc.egg-info/top_level.txt
iosxr_eznc/facts/__init__.py
iosxr_eznc/facts/personality.py
iosxr_eznc/facts/platform.py
iosxr_eznc/facts/shell.py
iosxr_eznc/utils/__init__.py
iosxr_eznc/utils/iosxr_yang_namespaces
iosxr_eznc/utils/namespaces.py